{
  "sights": [
    {
      "place_id": "ChIJF3PsrE41OkYRF6Bl_K5oZAw",
      "name": "Gamle Stavanger",
      "text": {
        "wiki": "",
        "brit": "",
        "quote": "Preserved 18th- & 19th-century white wooden cottages are the cornerstone of this historic district.",
        "tags": "['tourist_attraction', 'point_of_interest', 'establishment']",
        "website": {
          "source": "https://www.visitnorway.no/listings/gamle-stavanger/14660/",
          "content": ""
        }
      }
    },
    {
      "place_id": "ChIJl_cXA0w1OkYROVA2Thn-oLI",
      "name": "Norwegian Canning Museum",
      "text": {
        "wiki": "",
        "brit": "",
        "quote": "Exhibits, equipment demos & films on the regional canning industry in a former factory complex.",
        "tags": "['museum', 'tourist_attraction', 'point_of_interest', 'establishment']",
        "website": {
          "source": "http://norskhermetikkmuseum.no/",
          "content": ""
        }
      }
    },
    {
      "place_id": "ChIJF0boWEA1OkYRIPSxgOpAtw4",
      "name": "V\u00e5landst\u00e5rnet",
      "text": {
        "wiki": "",
        "brit": "",
        "quote": "",
        "tags": "['tourist_attraction', 'point_of_interest', 'establishment']",
        "website": {
          "source": "http://www.byhistoriskforening.org/byhistorisk_skilting/25_vaalandstaarnet",
          "content": ""
        }
      }
    },
    {
      "place_id": "ChIJfaQL6Ek1OkYRiXfgrlm22C4",
      "name": "Stavanger Cathedral",
      "text": {
        "wiki": "",
        "brit": "",
        "quote": "Elegant medieval cathedral, Norway's oldest, with Gothic & Romanesque accents & vivid stained glass.",
        "tags": "['tourist_attraction', 'church', 'place_of_worship', 'point_of_interest', 'establishment']",
        "website": {
          "source": "https://domkirkenogpetri.no/",
          "content": ""
        }
      }
    },
    {
      "place_id": "ChIJqdCi9Ec1OkYRfe4Ca6J_s8Q",
      "name": "Stavanger City Museum",
      "text": {
        "wiki": "",
        "brit": "",
        "quote": "Museum built in 1893 offering exhibits on local cultural & natural history, plus displays for kids.",
        "tags": "['museum', 'tourist_attraction', 'point_of_interest', 'establishment']",
        "website": {
          "source": "http://www.museumstavanger.no/",
          "content": ""
        }
      }
    },
    {
      "place_id": "ChIJPT_QEkk1OkYRiZdk1NOhE2w",
      "name": "Stavanger Maritime Museum",
      "text": {
        "wiki": "",
        "brit": "",
        "quote": "Small dockside museum featuring ship models & artifacts related to Stavanger's maritime history.",
        "tags": "['tourist_attraction', 'museum', 'point_of_interest', 'establishment']",
        "website": {
          "source": "http://www.stavangermaritimemuseum.no/",
          "content": ""
        }
      }
    },
    {
      "place_id": "ChIJ79v3eUo1OkYR2d39FDjMCwo",
      "name": "Norwegian Petroleum Museum",
      "text": {
        "wiki": "",
        "brit": "",
        "quote": "Petroleum museum by the port based in a stand-out landmark building built from different rocks.",
        "tags": "['museum', 'point_of_interest', 'establishment']",
        "website": {
          "source": "http://www.norskolje.museum.no/",
          "content": ""
        }
      }
    },
    {
      "place_id": "ChIJBYgCeEU1OkYR7DrB9dmYVV8",
      "name": "Breidablikk museum",
      "text": {
        "wiki": "",
        "brit": "",
        "quote": "Elegant 1881 manor featuring historic furnishings & antiques, plus English-style landscaped grounds.",
        "tags": "['museum', 'tourist_attraction', 'point_of_interest', 'establishment']",
        "website": {
          "source": "http://breidablikkmuseum.no/",
          "content": ""
        }
      }
    },
    {
      "place_id": "ChIJDyhiEUo1OkYRZS9ICqFksSQ",
      "name": "Fargegaten",
      "text": {
        "wiki": "",
        "brit": "",
        "quote": "",
        "tags": "['tourist_attraction', 'point_of_interest', 'establishment']",
        "website": {
          "source": "",
          "content": ""
        }
      }
    },
    {
      "place_id": "ChIJMdQklmA1OkYRy2Vk4c8GU40",
      "name": "Stavanger Art Museum",
      "text": {
        "wiki": "",
        "brit": "",
        "quote": "Lakeside, sophisticated museum offering Norwegian & international artworks dating back to the 1800s.",
        "tags": "['art_gallery', 'tourist_attraction', 'museum', 'point_of_interest', 'establishment']",
        "website": {
          "source": "http://stavangerkunstmuseum.no/",
          "content": ""
        }
      }
    },
    {
      "place_id": "ChIJOaGIh301OkYRIKZE6pS9UzU",
      "name": "Jernalderg\u00e5rden",
      "text": {
        "wiki": "",
        "brit": "",
        "quote": "Replica of an Iron Age farmstead, with costumed docents, demonstrations & hands-on kids' activities.",
        "tags": "['tourist_attraction', 'museum', 'point_of_interest', 'establishment']",
        "website": {
          "source": "http://am.uis.no/jernaldergarden/",
          "content": ""
        }
      }
    },
    {
      "place_id": "ChIJ3RV65Y5KOkYRiw81Mxv2FF4",
      "name": "Sverd i fjell",
      "text": {
        "wiki": "",
        "brit": "",
        "quote": "Fjord-side monument to the 872 Battle of Hafrsfjord, with 3 10m-tall swords, made in 1983.",
        "tags": "['tourist_attraction', 'point_of_interest', 'establishment']",
        "website": {
          "source": "https://www.visitnorway.com/listings/swords-in-rock/1852/",
          "content": ""
        }
      }
    },
    {
      "place_id": "ChIJk-9opEc1OkYR0_ng1ag5TsQ",
      "name": "Arkeologisk museum i Stavanger",
      "text": {
        "wiki": "",
        "brit": "",
        "quote": "Regionally focused archaeological & natural history exhibits dating to prehistoric times.",
        "tags": "['museum', 'tourist_attraction', 'point_of_interest', 'establishment']",
        "website": {
          "source": "http://www.arkeologiskmuseum.no/",
          "content": ""
        }
      }
    },
    {
      "place_id": "ChIJRSkLBnw1OkYReqZsVPLrZD4",
      "name": "Stavanger Botanical Garden",
      "text": {
        "wiki": "",
        "brit": "",
        "quote": "",
        "tags": "['tourist_attraction', 'park', 'point_of_interest', 'establishment']",
        "website": {
          "source": "http://www.stavanger.kommune.no/botaniskhage",
          "content": ""
        }
      }
    },
    {
      "place_id": "ChIJJ_mCfU81OkYRQE34KF5EY6I",
      "name": "LEDAAL",
      "text": {
        "wiki": "",
        "brit": "",
        "quote": "Grand, listed 1800s residence with Baroque gardens housing antique furniture & historic art.",
        "tags": "['museum', 'tourist_attraction', 'point_of_interest', 'establishment']",
        "website": {
          "source": "http://ledaal.no/en/informasjon",
          "content": ""
        }
      }
    },
    {
      "place_id": "ChIJbQhUHUo1OkYR80nbdFeiY-A",
      "name": "Norwegian Children's Museum",
      "text": {
        "wiki": "",
        "brit": "",
        "quote": "Institution with cultural & historical exhibits, plus a children's museum with hands-on displays.",
        "tags": "['museum', 'tourist_attraction', 'point_of_interest', 'establishment']",
        "website": {
          "source": "http://www.norskbarnemuseum.no/",
          "content": ""
        }
      }
    },
    {
      "place_id": "ChIJ0XygUno1OkYRrkdsGd0ufHk",
      "name": "Ullandhaugt\u00e5rnet",
      "text": {
        "wiki": "",
        "brit": "",
        "quote": "",
        "tags": "['tourist_attraction', 'point_of_interest', 'establishment']",
        "website": {
          "source": "https://www.visitnorway.no/listings/ullandhaugt%C3%A5rnet/14669/",
          "content": ""
        }
      }
    },
    {
      "place_id": "ChIJp3uL0XA1OkYR2C1XF4IKp-I",
      "name": "Kannik fotgjengerundergang street art",
      "text": {
        "wiki": "",
        "brit": "",
        "quote": "",
        "tags": "['tourist_attraction', 'point_of_interest', 'establishment']",
        "website": {
          "source": "",
          "content": ""
        }
      }
    },
    {
      "place_id": "ChIJBbEONXY1OkYRxxcoSEWkgz8",
      "name": "S\u00f8rmarka",
      "text": {
        "wiki": "",
        "brit": "",
        "quote": "",
        "tags": "['park', 'tourist_attraction', 'point_of_interest', 'establishment']",
        "website": {
          "source": "",
          "content": ""
        }
      }
    },
    {
      "place_id": "ChIJAQAHKUo1OkYRMnLVsyPhYrM",
      "name": "Valbergt\u00e5rnet",
      "text": {
        "wiki": "",
        "brit": "",
        "quote": "",
        "tags": "['tourist_attraction', 'point_of_interest', 'establishment']",
        "website": {
          "source": "",
          "content": ""
        }
      }
    },
    {
      "place_id": "ChIJ83MrmUk1OkYRLxgEoSbT3CQ",
      "name": "Sj\u00f8fartsmonumentet",
      "text": {
        "wiki": "",
        "brit": "",
        "quote": "",
        "tags": "['tourist_attraction', 'point_of_interest', 'establishment']",
        "website": {
          "source": "",
          "content": ""
        }
      }
    },
    {
      "place_id": "ChIJsZK4QC41OkYRtKVsu13gZg8",
      "name": "Freedome Trampoline park",
      "text": {
        "wiki": "",
        "brit": "",
        "quote": "",
        "tags": "['tourist_attraction', 'amusement_park', 'point_of_interest', 'establishment']",
        "website": {
          "source": "https://www.freedome.no/",
          "content": ""
        }
      }
    },
    {
      "place_id": "ChIJ-VEQXeNKOkYRODKUuKw1AL8",
      "name": "Fluberget",
      "text": {
        "wiki": "",
        "brit": "",
        "quote": "",
        "tags": "['tourist_attraction', 'point_of_interest', 'establishment']",
        "website": {
          "source": "http://stavanger.kommune.no/",
          "content": ""
        }
      }
    },
    {
      "place_id": "ChIJT8bqWyI1OkYRDEPwqk5kYeg",
      "name": "Godalen Beach",
      "text": {
        "wiki": "",
        "brit": "",
        "quote": "",
        "tags": "['park', 'tourist_attraction', 'point_of_interest', 'establishment']",
        "website": {
          "source": "https://www.stavanger.kommune.no/kultur-og-fritid/tur-og-natur/badeplasser/#godalen",
          "content": ""
        }
      }
    },
    {
      "place_id": "ChIJcQEHQPQ1OkYRNc5WSF3jnQM",
      "name": "Tanners sunken ship",
      "text": {
        "wiki": "",
        "brit": "",
        "quote": "",
        "tags": "['tourist_attraction', 'point_of_interest', 'establishment']",
        "website": {
          "source": "",
          "content": ""
        }
      }
    },
    {
      "place_id": "ChIJQ5z6Gkw1OkYRfp9QX4qrX1Y",
      "name": "Workers Cottage",
      "text": {
        "wiki": "",
        "brit": "",
        "quote": "",
        "tags": "['museum', 'tourist_attraction', 'point_of_interest', 'establishment']",
        "website": {
          "source": "http://norskhermetikkmuseum.no/en/events/arbeiderboligen",
          "content": ""
        }
      }
    },
    {
      "place_id": "ChIJ55MbATM1OkYRts5Btd20qQ4",
      "name": "Stavanger City Bridge",
      "text": {
        "wiki": "",
        "brit": "",
        "quote": "",
        "tags": "['tourist_attraction', 'point_of_interest', 'establishment']",
        "website": {
          "source": "",
          "content": ""
        }
      }
    },
    {
      "place_id": "ChIJRe5vTi41OkYRGYGwbobkv4g",
      "name": "Freedome Stavanger-\u00d8st",
      "text": {
        "wiki": "",
        "brit": "",
        "quote": "",
        "tags": "['amusement_park', 'tourist_attraction', 'point_of_interest', 'establishment']",
        "website": {
          "source": "http://www.freedome.no/",
          "content": ""
        }
      }
    },
    {
      "place_id": "ChIJzwHInBo1OkYR-HSrEBi2gMs",
      "name": "Stavanger skolemuseum",
      "text": {
        "wiki": "",
        "brit": "",
        "quote": "",
        "tags": "['museum', 'tourist_attraction', 'point_of_interest', 'establishment']",
        "website": {
          "source": "http://stavangerskolemuseum.no/",
          "content": ""
        }
      }
    },
    {
      "place_id": "ChIJBUuFuC41OkYRFPHzcMTBeyQ",
      "name": "TOU",
      "text": {
        "wiki": "",
        "brit": "",
        "quote": "",
        "tags": "['tourist_attraction', 'point_of_interest', 'establishment']",
        "website": {
          "source": "http://touofficial.com/",
          "content": ""
        }
      }
    },
    {
      "place_id": "ChIJzT74fjY1OkYRjKhGI9e40sc",
      "name": "Reidar Berge Museum",
      "text": {
        "wiki": "",
        "brit": "",
        "quote": "",
        "tags": "['museum', 'tourist_attraction', 'point_of_interest', 'establishment']",
        "website": {
          "source": "https://norge.sandalsand.net/reidar-berge-museet-i-stavanger/",
          "content": ""
        }
      }
    },
    {
      "place_id": "ChIJf19M3kVLOkYRRMUCfzQHzD0",
      "name": "FuMG-65 W\u00fcrzburg-Riese",
      "text": {
        "wiki": "",
        "brit": "",
        "quote": "",
        "tags": "['tourist_attraction', 'point_of_interest', 'establishment']",
        "website": {
          "source": "",
          "content": ""
        }
      }
    },
    {
      "place_id": "ChIJlfcp3Uk1OkYRWZIKuCHreq0",
      "name": "Stavanger",
      "text": {
        "wiki": "",
        "brit": "Stavanger,  city and seaport, southwestern Norway. It is situated on the east side of a peninsula, with the Norwegian Sea on the west and Gands Fjord, a south branch of broad Bokna Fjord, on the east. Stavanger became the seat of a bishopric in the 12th century, when the Cathedral of St. Swithun was built. Although it received a royal charter as a trading town in 1425, Stavanger grew very slowly. After the Protestant Reformation, its bishopric was transferred to Kristiansand in 1682, but a new Lutheran bishopric was established in Stavanger in 1925.StavangerStavanger, Nor.\u00a9 Nightman1965/Shutterstock.com\n\n\n\n\n\n\nBritannica Quiz\nPassport to Europe\nWhat is the capital of Slovenia?\n\n\n\nShipbuilding and shipping are the city\u2019s chief economic activities, together with the refining of North Sea oil, first drilled in 1971. Stavanger became the centre for all service activities connected with Norway\u2019s burgeoning North Sea oil and gas industry. Its protected ice-free harbour is the closest major Norwegian port to Great Britain. Food processing, especially the canning of sardines and other fish products, was formerly an important industry. The Norwegian Canning Museum is one of several local museums that together constitute Museum Stavanger. Among the others are the Norwegian Petroleum Museum, Stavanger Museum, Stavanger Maritime Museum, and Stavanger Art Museum. Stavanger is also the site of the Kongsg\u00e5rd Grammar School (formerly a royal residence) and the Valbergt\u00e5rn Watchtower. The Cathedral of St. Swithun, with its Norman and Gothic architecture, is another popular tourist attraction. Stavanger is the gateway to the J\u00e6ren agricultural district, lying to the south of the city. Pop. (2007 est.) mun., 117,315. ",
        "quote": "",
        "tags": "['locality', 'political']",
        "website": {
          "source": "",
          "content": ""
        }
      }
    },
    {
      "place_id": "ChIJwXmhJUg1OkYRspnr4WpQ-QA",
      "name": "Breiavatnet",
      "text": {
        "wiki": "",
        "brit": "",
        "quote": "",
        "tags": "['natural_feature', 'establishment']",
        "website": {
          "source": "",
          "content": ""
        }
      }
    },
    {
      "place_id": "ChIJY7g6a101OkYRPyQlXTRzJlE",
      "name": "Mosvatnet",
      "text": {
        "wiki": "",
        "brit": "",
        "quote": "",
        "tags": "['natural_feature', 'establishment']",
        "website": {
          "source": "",
          "content": ""
        }
      }
    },
    {
      "place_id": "ChIJUXlnbRg0OkYRpYnktJRVeh4",
      "name": "Dalsnuten",
      "text": {
        "wiki": "",
        "brit": "",
        "quote": "",
        "tags": "['tourist_attraction', 'point_of_interest', 'establishment']",
        "website": {
          "source": "https://ut.no/turforslag/116597/dalsnuten",
          "content": ""
        }
      }
    },
    {
      "place_id": "ChIJZXPsbDY1OkYRPXMYrXMcfWA",
      "name": "St Petri kirke",
      "text": {
        "wiki": "",
        "brit": "",
        "quote": "",
        "tags": "['church', 'tourist_attraction', 'place_of_worship', 'point_of_interest', 'establishment']",
        "website": {
          "source": "http://www.domkirkenogpetri.no/",
          "content": ""
        }
      }
    },
    {
      "place_id": "ChIJb_zxL0g1OkYRT0_egaXSrKE",
      "name": "Breiavatnet",
      "text": {
        "wiki": "",
        "brit": "",
        "quote": "",
        "tags": "['park', 'point_of_interest', 'establishment']",
        "website": {
          "source": "",
          "content": ""
        }
      }
    },
    {
      "place_id": "ChIJ-REm1Ec1OkYRPV9sKHKMwJQ",
      "name": "St Svithun's Church, Stavanger",
      "text": {
        "wiki": "",
        "brit": "",
        "quote": "Glass details flood this modern Catholic church with light during its regular services.",
        "tags": "['tourist_attraction', 'church', 'place_of_worship', 'point_of_interest', 'establishment']",
        "website": {
          "source": "http://stavanger.katolsk.no/",
          "content": ""
        }
      }
    },
    {
      "place_id": "ChIJUd07Ey9KOkYRbqn2j-17WXo",
      "name": "Sola flytekniske museum",
      "text": {
        "wiki": "",
        "brit": "",
        "quote": "",
        "tags": "['museum', 'tourist_attraction', 'point_of_interest', 'establishment']",
        "website": {
          "source": "https://www.jaermuseet.no/flyhistorisk/",
          "content": ""
        }
      }
    },
    {
      "place_id": "ChIJRfLZzUs1OkYRCeFVmpak3_I",
      "name": "R\u00f8dne Fjord Cruise",
      "text": {
        "wiki": "",
        "brit": "",
        "quote": "",
        "tags": "['travel_agency', 'point_of_interest', 'establishment']",
        "website": {
          "source": "http://www.rodne.no/",
          "content": ""
        }
      }
    },
    {
      "place_id": "ChIJERSZQEk1OkYRS5B2U33hwbk",
      "name": "Lendeparken",
      "text": {
        "wiki": "",
        "brit": "",
        "quote": "",
        "tags": "['park', 'point_of_interest', 'establishment']",
        "website": {
          "source": "",
          "content": ""
        }
      }
    },
    {
      "place_id": "ChIJVZf-gqQ1OkYRNIk-KnuV0fg",
      "name": "Viking House",
      "text": {
        "wiki": "",
        "brit": "",
        "quote": "",
        "tags": "['travel_agency', 'point_of_interest', 'establishment']",
        "website": {
          "source": "https://www.vikinghouse.no/",
          "content": ""
        }
      }
    },
    {
      "place_id": "ChIJERQ9Jau0O0YRES2LTP9aEfU",
      "name": "Vistnestunet",
      "text": {
        "wiki": "",
        "brit": "",
        "quote": "",
        "tags": "['tourist_attraction', 'point_of_interest', 'establishment']",
        "website": {
          "source": "https://www.jaermuseet.no/vistnestunet/",
          "content": ""
        }
      }
    },
    {
      "place_id": "ChIJM0ogaNc1OkYRsuUeCWThxpo",
      "name": "Leo's Lekeland",
      "text": {
        "wiki": "",
        "brit": "",
        "quote": "",
        "tags": "['tourist_attraction', 'cafe', 'restaurant', 'food', 'point_of_interest', 'establishment']",
        "website": {
          "source": "https://www.leoslekeland.no/stavanger/",
          "content": ""
        }
      }
    },
    {
      "place_id": "ChIJh1XtE0k1OkYRXRNH0O9RjdQ",
      "name": "Groombr\u00f8nnen",
      "text": {
        "wiki": "",
        "brit": "",
        "quote": "",
        "tags": "['point_of_interest', 'establishment']",
        "website": {
          "source": "",
          "content": ""
        }
      }
    },
    {
      "place_id": "ChIJUWqwa2A1OkYRRdDaS6Nar-w",
      "name": "IMI Church",
      "text": {
        "wiki": "",
        "brit": "",
        "quote": "",
        "tags": "['church', 'tourist_attraction', 'place_of_worship', 'point_of_interest', 'establishment']",
        "website": {
          "source": "http://www.imikirken.no/",
          "content": ""
        }
      }
    },
    {
      "place_id": "ChIJBfqojU01OkYR2dBs3h4n6Es",
      "name": "Hertervighuset",
      "text": {
        "wiki": "",
        "brit": "",
        "quote": "",
        "tags": "['point_of_interest', 'establishment']",
        "website": {
          "source": "http://www.norge.sandalsand.net/hertervighusene-i-stavanger/",
          "content": ""
        }
      }
    },
    {
      "place_id": "ChIJ14Jn_kk1OkYRUbJ2hW_jdpU",
      "name": "S\u00f8lvbergtorget",
      "text": {
        "wiki": "",
        "brit": "",
        "quote": "",
        "tags": "['park', 'point_of_interest', 'establishment']",
        "website": {
          "source": "",
          "content": ""
        }
      }
    },
    {
      "place_id": "ChIJ5ewAPEVLOkYRQxYNEMa8Tu4",
      "name": "Helleristningene ved Kvernevik",
      "text": {
        "wiki": "",
        "brit": "",
        "quote": "",
        "tags": "['tourist_attraction', 'point_of_interest', 'establishment']",
        "website": {
          "source": "https://kulturminnesok.no/minne?queryString=https://data.kulturminne.no/askeladden/lokalitet/24609",
          "content": ""
        }
      }
    },
    {
      "place_id": "ChIJ2a9_lkc1OkYRzHhCwBd2d9Y",
      "name": "Sykehusparken",
      "text": {
        "wiki": "",
        "brit": "",
        "quote": "",
        "tags": "['park', 'point_of_interest', 'establishment']",
        "website": {
          "source": "",
          "content": ""
        }
      }
    },
    {
      "place_id": "ChIJOaGIh301OkYRFvTOktvWbH4",
      "name": "Iron Age Farm",
      "text": {
        "wiki": "",
        "brit": "",
        "quote": "",
        "tags": "['museum', 'point_of_interest', 'establishment']",
        "website": {
          "source": "https://am.uis.no/jernaldergarden/",
          "content": ""
        }
      }
    },
    {
      "place_id": "ChIJt5I08Ek1OkYRC2cCLjkCUrE",
      "name": "Arneageren",
      "text": {
        "wiki": "",
        "brit": "",
        "quote": "",
        "tags": "['park', 'point_of_interest', 'establishment']",
        "website": {
          "source": "",
          "content": ""
        }
      }
    },
    {
      "place_id": "ChIJa7AoWU01OkYRzRTOSzBXQwM",
      "name": "Bjergstedparken",
      "text": {
        "wiki": "",
        "brit": "",
        "quote": "",
        "tags": "['park', 'point_of_interest', 'establishment']",
        "website": {
          "source": "http://www.bjergsted.no/",
          "content": ""
        }
      }
    },
    {
      "place_id": "ChIJzxKv4-dLOkYR0hzYpMu0NfE",
      "name": "Gravr\u00f8ys fra jernalder",
      "text": {
        "wiki": "",
        "brit": "",
        "quote": "",
        "tags": "['tourist_attraction', 'point_of_interest', 'establishment']",
        "website": {
          "source": "https://kulturminnesok.no/minne?queryString=https://data.kulturminne.no/askeladden/lokalitet/65780",
          "content": ""
        }
      }
    },
    {
      "place_id": "ChIJg-dZKjY1OkYRCXUyZKXhey0",
      "name": "Paviljongen",
      "text": {
        "wiki": "",
        "brit": "",
        "quote": "",
        "tags": "['park', 'point_of_interest', 'establishment']",
        "website": {
          "source": "",
          "content": ""
        }
      }
    },
    {
      "place_id": "ChIJUcKnKdY1OkYRbxDj-eU0gsE",
      "name": "Lifjell view over Stavanger",
      "text": {
        "wiki": "",
        "brit": "",
        "quote": "",
        "tags": "['tourist_attraction', 'point_of_interest', 'establishment']",
        "website": {
          "source": "",
          "content": ""
        }
      }
    },
    {
      "place_id": "ChIJ69Sy1aY1OkYRcoZw9s-LjBk",
      "name": "Mosvatnet Park",
      "text": {
        "wiki": "",
        "brit": "",
        "quote": "",
        "tags": "['park', 'point_of_interest', 'establishment']",
        "website": {
          "source": "",
          "content": ""
        }
      }
    },
    {
      "place_id": "ChIJ8xTMyEc1OkYRhqxeL2tWriE",
      "name": "Kannikparken",
      "text": {
        "wiki": "",
        "brit": "",
        "quote": "",
        "tags": "['park', 'point_of_interest', 'establishment']",
        "website": {
          "source": "",
          "content": ""
        }
      }
    }
  ]
}